kombat/__init__.py
kombat/crawlers/__init__.py
kombat/crawlers/system_crawler.py
kombat-0.1.2.dist-info/METADATA
kombat-0.1.2.dist-info/WHEEL
kombat-0.1.2.dist-info/licenses/LICENSE
kombat-0.1.2.dist-info/RECORD
